{"cameraMode":{"drawMode":0,"name":"Shaded","section":"Shading Mode"},"sceneLighting":true,"audioPlay":false,"sceneViewState":{"showFog":true,"showMaterialUpdate":false,"showSkybox":true,"showFlares":true,"showImageEffects":true,"showParticleSystems":true},"in2DMode":false,"pivot":{"x":0.047550082206726077,"y":0.4422075152397156,"z":3.549980640411377},"rotation":{"x":-0.20317430794239045,"y":-0.22476574778556825,"z":0.047979842871427539,"w":-0.9517868757247925},"size":0.9639241099357605,"orthographic":false}